smops/__init__.py
smops/cmdline.py
smops/schema.yml
smops/smooth.py
smops-0.1.7.dist-info/METADATA
smops-0.1.7.dist-info/WHEEL
smops-0.1.7.dist-info/entry_points.txt
smops-0.1.7.dist-info/top_level.txt
smops-0.1.7.dist-info/RECORD
