Metadata-Version: 2.1
Name: smops
Version: 0.1.7
Summary: Python script for interpolating FITS model images over frequency
Home-page: https://github.com/mulan-94/smops
Author: L. Andati
License: MIT license
Keywords: smops,model frequency interpolation,FITS images
Classifier: Development Status :: 4 - Beta
Classifier: Intended Audience :: Developers
Classifier: Intended Audience :: Science/Research
Classifier: License :: OSI Approved :: MIT License
Classifier: Natural Language :: English
Classifier: Programming Language :: Python :: 3.8
Classifier: Programming Language :: Python :: 3.9
Classifier: Programming Language :: Python :: 3.10
Requires-Dist: astropy
Requires-Dist: dask
Requires-Dist: python-casacore
Requires-Dist: psutil
Requires-Dist: numpy
Requires-Dist: stimela (==2.0rc4)
